{
    "/js/admin/admin.js": "/js/admin/admin.js",
    "/js/admin/manifest.js": "/js/admin/manifest.js",
    "/js/admin/vendor.js": "/js/admin/vendor.js",
    "/js/components/button-close.js": "/js/components/button-close.js",
    "/js/components/button-icons.js": "/js/components/button-icons.js",
    "/js/components/button-menu.js": "/js/components/button-menu.js",
    "/js/pages/admin/app-tracking.js": "/js/pages/admin/app-tracking.js",
    "/js/pages/admin/app-tracking~js/pages/admin/blog/post/create~js/pages/admin/blog/post/edit~js/pages/a~12af0bf4.js": "/js/pages/admin/app-tracking~js/pages/admin/blog/post/create~js/pages/admin/blog/post/edit~js/pages/a~12af0bf4.js",
    "/js/pages/admin/app-tracking~js/pages/admin/content/general-information~js/pages/admin/services/creat~05fc4f31.js": "/js/pages/admin/app-tracking~js/pages/admin/content/general-information~js/pages/admin/services/creat~05fc4f31.js",
    "/js/pages/admin/blog/category.js": "/js/pages/admin/blog/category.js",
    "/js/pages/admin/blog/category~js/pages/admin/blog/post/create~js/pages/admin/blog/post/edit~js/pages/~d689a397.js": "/js/pages/admin/blog/category~js/pages/admin/blog/post/create~js/pages/admin/blog/post/edit~js/pages/~d689a397.js",
    "/js/pages/admin/blog/category~js/pages/admin/blog/post/create~js/pages/admin/blog/post/index~js/pages~3689c3b4.js": "/js/pages/admin/blog/category~js/pages/admin/blog/post/create~js/pages/admin/blog/post/index~js/pages~3689c3b4.js",
    "/js/pages/admin/blog/category~js/pages/admin/blog/post/index~js/pages/admin/configuration/general~js/~d5c29e09.js": "/js/pages/admin/blog/category~js/pages/admin/blog/post/index~js/pages/admin/configuration/general~js/~d5c29e09.js",
    "/js/pages/admin/blog/category~js/pages/admin/blog/post/index~js/pages/admin/encuesta~js/pages/admin/l~837b1c3f.js": "/js/pages/admin/blog/category~js/pages/admin/blog/post/index~js/pages/admin/encuesta~js/pages/admin/l~837b1c3f.js",
    "/js/pages/admin/blog/post/create.js": "/js/pages/admin/blog/post/create.js",
    "/js/pages/admin/blog/post/create~js/pages/admin/blog/post/edit~js/pages/admin/content/seo~js/pages/ad~74aac823.js": "/js/pages/admin/blog/post/create~js/pages/admin/blog/post/edit~js/pages/admin/content/seo~js/pages/ad~74aac823.js",
    "/js/pages/admin/blog/post/edit.js": "/js/pages/admin/blog/post/edit.js",
    "/js/pages/admin/blog/post/index.js": "/js/pages/admin/blog/post/index.js",
    "/js/pages/admin/configuration/general.js": "/js/pages/admin/configuration/general.js",
    "/js/pages/admin/configuration/general~js/pages/admin/content/social-networks~js/pages/admin/encuesta.js": "/js/pages/admin/configuration/general~js/pages/admin/content/social-networks~js/pages/admin/encuesta.js",
    "/js/pages/admin/content/general-content.js": "/js/pages/admin/content/general-content.js",
    "/js/pages/admin/content/general-information.js": "/js/pages/admin/content/general-information.js",
    "/js/pages/admin/content/general-information~js/pages/admin/sucursales.js": "/js/pages/admin/content/general-information~js/pages/admin/sucursales.js",
    "/js/pages/admin/content/seo.js": "/js/pages/admin/content/seo.js",
    "/js/pages/admin/content/social-networks.js": "/js/pages/admin/content/social-networks.js",
    "/js/pages/admin/customers.js": "/js/pages/admin/customers.js",
    "/js/pages/admin/dashboard.js": "/js/pages/admin/dashboard.js",
    "/js/pages/admin/editor.js": "/js/pages/admin/editor.js",
    "/js/pages/admin/encuesta.js": "/js/pages/admin/encuesta.js",
    "/js/pages/admin/faqs.js": "/js/pages/admin/faqs.js",
    "/js/pages/admin/lead/traditional.js": "/js/pages/admin/lead/traditional.js",
    "/js/pages/admin/login.js": "/js/pages/admin/login.js",
    "/js/pages/admin/profile.js": "/js/pages/admin/profile.js",
    "/js/pages/admin/reset.js": "/js/pages/admin/reset.js",
    "/js/pages/admin/services/create.js": "/js/pages/admin/services/create.js",
    "/js/pages/admin/services/edit.js": "/js/pages/admin/services/edit.js",
    "/js/pages/admin/services/index.js": "/js/pages/admin/services/index.js",
    "/js/pages/admin/services/read.js": "/js/pages/admin/services/read.js",
    "/js/pages/admin/sucursales.js": "/js/pages/admin/sucursales.js",
    "/js/pages/admin/testimonials.js": "/js/pages/admin/testimonials.js",
    "/js/pages/admin/tutorials.js": "/js/pages/admin/tutorials.js",
    "/js/pages/admin/users.js": "/js/pages/admin/users.js",
    "/vendors~js/pages/admin/app-tracking~js/pages/admin/blog/category~js/pages/admin/blog/post/create~js/~b6d7522b.js": "/vendors~js/pages/admin/app-tracking~js/pages/admin/blog/category~js/pages/admin/blog/post/create~js/~b6d7522b.js",
    "/vendors~js/pages/admin/app-tracking~js/pages/admin/blog/category~js/pages/admin/blog/post/index~js/p~d5fbef94.js": "/vendors~js/pages/admin/app-tracking~js/pages/admin/blog/category~js/pages/admin/blog/post/index~js/p~d5fbef94.js",
    "/vendors~js/pages/admin/app-tracking~js/pages/admin/blog/post/create~js/pages/admin/blog/post/edit~js~250156e5.js": "/vendors~js/pages/admin/app-tracking~js/pages/admin/blog/post/create~js/pages/admin/blog/post/edit~js~250156e5.js",
    "/vendors~js/pages/admin/app-tracking~js/pages/admin/blog/post/create~js/pages/admin/blog/post/edit~js~aaa3a9eb.js": "/vendors~js/pages/admin/app-tracking~js/pages/admin/blog/post/create~js/pages/admin/blog/post/edit~js~aaa3a9eb.js",
    "/vendors~js/pages/admin/app-tracking~js/pages/admin/blog/post/create~js/pages/admin/blog/post/edit~js~c21ed78c.js": "/vendors~js/pages/admin/app-tracking~js/pages/admin/blog/post/create~js/pages/admin/blog/post/edit~js~c21ed78c.js",
    "/vendors~js/pages/admin/blog/category~js/pages/admin/blog/post/index~js/pages/admin/configuration/gen~06f4f720.js": "/vendors~js/pages/admin/blog/category~js/pages/admin/blog/post/index~js/pages/admin/configuration/gen~06f4f720.js",
    "/vendors~js/pages/admin/blog/post/create~js/pages/admin/blog/post/edit.js": "/vendors~js/pages/admin/blog/post/create~js/pages/admin/blog/post/edit.js",
    "/vendors~js/pages/admin/blog/post/create~js/pages/admin/blog/post/edit~js/pages/admin/dashboard~js/pa~500bcb7c.js": "/vendors~js/pages/admin/blog/post/create~js/pages/admin/blog/post/edit~js/pages/admin/dashboard~js/pa~500bcb7c.js",
    "/vendors~js/pages/admin/configuration/general~js/pages/admin/content/social-networks~js/pages/admin/c~3062200a.js": "/vendors~js/pages/admin/configuration/general~js/pages/admin/content/social-networks~js/pages/admin/c~3062200a.js",
    "/vendors~js/pages/admin/dashboard.js": "/vendors~js/pages/admin/dashboard.js"
}
